fasthdl/__init__.py
fasthdl/fasthdl.py
fasthdl-0.0.1.dist-info/LICENSE
fasthdl-0.0.1.dist-info/METADATA
fasthdl-0.0.1.dist-info/WHEEL
fasthdl-0.0.1.dist-info/top_level.txt
fasthdl-0.0.1.dist-info/RECORD
